automation_file/__init__.py
automation_file/__main__.py
automation_file/local/__init__.py
automation_file/local/dir/__init__.py
automation_file/local/dir/dir_process.py
automation_file/local/file/__init__.py
automation_file/local/file/file_process.py
automation_file/local/zip/__init__.py
automation_file/local/zip/zip_process.py
automation_file/remote/__init__.py
automation_file/remote/download/__init__.py
automation_file/remote/download/file.py
automation_file/remote/google_drive/__init__.py
automation_file/remote/google_drive/driver_instance.py
automation_file/remote/google_drive/delete/__init__.py
automation_file/remote/google_drive/delete/delete_manager.py
automation_file/remote/google_drive/dir/__init__.py
automation_file/remote/google_drive/dir/folder_manager.py
automation_file/remote/google_drive/download/__init__.py
automation_file/remote/google_drive/download/download_file.py
automation_file/remote/google_drive/search/__init__.py
automation_file/remote/google_drive/search/search_drive.py
automation_file/remote/google_drive/share/__init__.py
automation_file/remote/google_drive/share/share_file.py
automation_file/remote/google_drive/upload/__init__.py
automation_file/remote/google_drive/upload/upload_to_driver.py
automation_file/utils/__init__.py
automation_file/utils/callback/__init__.py
automation_file/utils/callback/callback_function_executor.py
automation_file/utils/exception/__init__.py
automation_file/utils/exception/exception_tags.py
automation_file/utils/exception/exceptions.py
automation_file/utils/executor/__init__.py
automation_file/utils/executor/action_executor.py
automation_file/utils/file_process/__init__.py
automation_file/utils/file_process/get_dir_file_list.py
automation_file/utils/json/__init__.py
automation_file/utils/json/json_file.py
automation_file/utils/logging/__init__.py
automation_file/utils/logging/loggin_instance.py
automation_file/utils/package_manager/__init__.py
automation_file/utils/package_manager/package_manager_class.py
automation_file-0.0.29.dist-info/licenses/LICENSE
automation_file-0.0.29.dist-info/METADATA
automation_file-0.0.29.dist-info/WHEEL
automation_file-0.0.29.dist-info/top_level.txt
automation_file-0.0.29.dist-info/RECORD
