Metadata-Version: 2.4
Name: automation_file
Version: 0.0.29
Author-email: JE-Chen <zenmailman@gmail.com>
Project-URL: Homepage, https://github.com/JE-Chen/Integration-testing-environment
Classifier: Programming Language :: Python :: 3.10
Classifier: Development Status :: 2 - Pre-Alpha
Classifier: Environment :: Win32 (MS Windows)
Classifier: Environment :: MacOS X
Classifier: Environment :: X11 Applications
Classifier: Operating System :: OS Independent
Requires-Python: >=3.10
License-File: LICENSE
Requires-Dist: google-api-python-client
Requires-Dist: google-auth-httplib2
Requires-Dist: google-auth-oauthlib
Requires-Dist: requests
Requires-Dist: tqdm
Dynamic: license-file
